s3hop/__init__.py
s3hop/cli.py
s3hop/core.py
s3hop-0.1.2.dist-info/LICENSE
s3hop-0.1.2.dist-info/METADATA
s3hop-0.1.2.dist-info/WHEEL
s3hop-0.1.2.dist-info/entry_points.txt
s3hop-0.1.2.dist-info/top_level.txt
s3hop-0.1.2.dist-info/RECORD
