Metadata-Version: 2.1
Name: s3hop
Version: 0.1.2
Summary: A tool to copy files between S3 buckets across AWS accounts
Home-page: https://github.com/thehamsti/s3hop
Author: John Cummings
Author-email: john@hamsti.co
License: MIT
Classifier: Intended Audience :: Developers
Classifier: License :: OSI Approved :: MIT License
Classifier: Operating System :: OS Independent
Classifier: Programming Language :: Python :: 3
Classifier: Programming Language :: Python :: 3.6
Classifier: Programming Language :: Python :: 3.7
Classifier: Programming Language :: Python :: 3.8
Classifier: Programming Language :: Python :: 3.9
Classifier: Programming Language :: Python :: 3.10
Classifier: Programming Language :: Python :: 3.11
Classifier: Programming Language :: Python :: 3.12
Requires-Python: >=3.6
License-File: LICENSE
Requires-Dist: boto3>=1.26.0
Requires-Dist: botocore>=1.29.0
Requires-Dist: tqdm>=4.65.0
Requires-Dist: humanize>=4.6.0
Provides-Extra: dev
Requires-Dist: pytest>=7.0.0; extra == "dev"
Requires-Dist: pytest-cov>=4.0.0; extra == "dev"
Requires-Dist: black>=22.0.0; extra == "dev"
Requires-Dist: isort>=5.0.0; extra == "dev"
Requires-Dist: flake8>=4.0.0; extra == "dev"
Requires-Dist: build>=0.10.0; extra == "dev"
Requires-Dist: twine>=4.0.0; extra == "dev"
